MANIFEST.in
README.md
setup.cfg
setup.py
maskflow/__init__.py
maskflow/_version.py
maskflow/archive.py
maskflow/cococreator.py
maskflow/config.py
maskflow/config.yaml
maskflow/dataset.py
maskflow/inference.py
maskflow/model.py
maskflow/paths_catalog.py
maskflow/training.py
maskflow/utils.py
maskflow/viz.py
maskflow.egg-info/PKG-INFO
maskflow.egg-info/SOURCES.txt
maskflow.egg-info/dependency_links.txt
maskflow.egg-info/top_level.txt