Metadata-Version: 1.1
Name: maskflow
Version: 0.1.2
Summary: Object Detection and Segmentation for Cell Biology.
Home-page: https://github.com/hadim/maskflow/
Author: Hadrien Mary
Author-email: hadrien.mary@gmail.com
License: UNKNOWN
Platform: UNKNOWN
Classifier: Development Status :: 5 - Production/Stable
Classifier: Natural Language :: English
Classifier: License :: OSI Approved :: BSD License
Classifier: Operating System :: OS Independent
Classifier: Programming Language :: Python
Classifier: Programming Language :: Python :: 3
